{"nickname":"string","startTimeUtc":"2021-04-22T16:58:11.1001623Z","tournament":{"players":[{"playerId":"5527cf44a3a64428d4b6edf9","playerName":"AxelBaxel","totalPoints":36299,"games":[{"gamePoints":14261},{"gamePoints":22038}]},{"playerId":"5f931ed7c00e2400014430c9","playerName":"emi_1312","totalPoints":34648,"games":[{"gamePoints":14350},{"gamePoints":20298}]},{"playerId":"5e8609cb3d4b6a3cf8dcfc9c","playerName":"HugoCL","totalPoints":33075,"games":[{"gamePoints":12365},{"gamePoints":20710}]},{"playerId":"57832f3322054780403ba592","playerName":"HectorHTC","totalPoints":32610,"games":[{"gamePoints":14649},{"gamePoints":17961}]},{"playerId":"5be9cbd71f3cf81af810ab67","playerName":"Shark0s","totalPoints":32595,"games":[{"gamePoints":17437},{"gamePoints":15158}]},{"playerId":"5ffc9e5f4a5efa00015dd50b","playerName":"carnarfi","totalPoints":30449,"games":[{"gamePoints":14496},{"gamePoints":15953}]},{"playerId":"5f9329845f4b3600017951e5","playerName":"mat","totalPoints":29912,"games":[{"gamePoints":15159},{"gamePoints":14753}]},{"playerId":"5a4e3f8057f1750a400a8050","playerName":"Gorka1311","totalPoints":28724,"games":[{"gamePoints":8597},{"gamePoints":20127}]},{"playerId":"5783a7e0344dc34398cac4c4","playerName":"tfl","totalPoints":28351,"games":[{"gamePoints":9604},{"gamePoints":18747}]},{"playerId":"605ba9ca9f11430001849351","playerName":"Luckylae","totalPoints":20040,"games":[{"gamePoints":11850},{"gamePoints":8190}]},{"playerId":"60353d3eed952600012c0464","playerName":"DJTonyRH","totalPoints":18864,"games":[{"gamePoints":8578},{"gamePoints":10286}]},{"playerId":"5ef940c95f12bd8244134bb2","playerName":"Anyelo Aldair Amaya Castro","totalPoints":16902,"games":[{"gamePoints":14069},{"gamePoints":2833}]},{"playerId":"6058a96972a5a9000142195c","playerName":"dembelebalondeoro","totalPoints":16410,"games":[{"gamePoints":8548},{"gamePoints":7862}]},{"playerId":"6039398f5cdb1b0001baf058","playerName":"EquisPY","totalPoints":16160,"games":[{"gamePoints":null},{"gamePoints":16160}]},{"playerId":"571802f3c974ed353ccf1bd6","playerName":"Clara Hhh","totalPoints":11233,"games":[{"gamePoints":null},{"gamePoints":11233}]}]},"games":[{"allGuesses":[[{"playerName":"AxelBaxel","playerId":"5527cf44a3a64428d4b6edf9","roundScoreInPoints":3952,"distanceInMeters":436013.1591899522,"time":11,"lat":51.42424115550845,"lng":-104.57930362033142},{"playerName":"HugoCL","playerId":"5e8609cb3d4b6a3cf8dcfc9c","roundScoreInPoints":3168,"distanceInMeters":846007.6432367056,"time":24,"lat":41.67311912298503,"lng":-99.55496632429583},{"playerName":"emi_1312","playerId":"5f931ed7c00e2400014430c9","roundScoreInPoints":3073,"distanceInMeters":902060.7407222206,"time":27,"lat":51.73628558175964,"lng":-111.60707296619017},{"playerName":"Gorka1311","playerId":"5a4e3f8057f1750a400a8050","roundScoreInPoints":3034,"distanceInMeters":925839.4161851422,"time":17,"lat":51.486230353320906,"lng":-112.04135071041591},{"playerName":"tfl","playerId":"5783a7e0344dc34398cac4c4","roundScoreInPoints":2622,"distanceInMeters":1196552.7917952938,"time":30,"lat":38.94459067224418,"lng":-95.24009150450581},{"playerName":"HectorHTC","playerId":"57832f3322054780403ba592","roundScoreInPoints":3908,"distanceInMeters":456659.9600699421,"time":27,"lat":51.691369451071694,"lng":-104.65957954760803},{"playerName":"EquisPY","playerId":"6039398f5cdb1b0001baf058","roundScoreInPoints":3306,"distanceInMeters":766922.947925885,"time":29,"lat":43.513740677162865,"lng":-104.92664773821224},{"playerName":"carnarfi","playerId":"5ffc9e5f4a5efa00015dd50b","roundScoreInPoints":76,"distanceInMeters":7762500.21484518,"time":28,"lat":47.88483621818123,"lng":20.319437292900545},{"playerName":"Shark0s","playerId":"5be9cbd71f3cf81af810ab67","roundScoreInPoints":97,"distanceInMeters":7312023.694553043,"time":30,"lat":51.10548923961022,"lng":16.53052761769851},{"playerName":"mat","playerId":"5f9329845f4b3600017951e5","roundScoreInPoints":50,"distanceInMeters":8532078.412115974,"time":22,"lat":52.22639124448712,"lng":58.21402220693181},{"playerName":"Clara Hhh","playerId":"571802f3c974ed353ccf1bd6","roundScoreInPoints":89,"distanceInMeters":7468012.234321208,"time":22,"lat":58.27479511090349,"lng":38.97253400398055},{"playerName":"DJTonyRH","playerId":"60353d3eed952600012c0464","roundScoreInPoints":4,"distanceInMeters":13231199.980691666,"time":21,"lat":-42.017518956383526,"lng":173.24756236002798},{"playerName":"Luckylae","playerId":"605ba9ca9f11430001849351","roundScoreInPoints":73,"distanceInMeters":7840640.703220335,"time":16,"lat":46.50368012265972,"lng":19.35368668823571},{"playerName":"dembelebalondeoro","playerId":"6058a96972a5a9000142195c","roundScoreInPoints":718,"distanceInMeters":3597539.050403754,"time":23,"lat":17.08103027571817,"lng":-95.54829641962522},{"playerName":"Anyelo Aldair Amaya Castro","playerId":"5ef940c95f12bd8244134bb2","roundScoreInPoints":174,"distanceInMeters":6219864.469651457,"time":30,"lat":53.350516422304324,"lng":-2.3544649899268766}],[{"playerName":"AxelBaxel","playerId":"5527cf44a3a64428d4b6edf9","roundScoreInPoints":4623,"distanceInMeters":145213.7356520749,"time":12,"lat":3.1510827339164766,"lng":113.3470363824249},{"playerName":"HugoCL","playerId":"5e8609cb3d4b6a3cf8dcfc9c","roundScoreInPoints":4207,"distanceInMeters":320030.1080689482,"time":19,"lat":2.251666611309668,"lng":111.98041611670068},{"playerName":"emi_1312","playerId":"5f931ed7c00e2400014430c9","roundScoreInPoints":4088,"distanceInMeters":373039.5794613246,"time":25,"lat":1.990774793926966,"lng":111.57129736323873},{"playerName":"Gorka1311","playerId":"5a4e3f8057f1750a400a8050","roundScoreInPoints":3998,"distanceInMeters":414739.315179931,"time":15,"lat":3.02545977244807,"lng":110.52589965283923},{"playerName":"tfl","playerId":"5783a7e0344dc34398cac4c4","roundScoreInPoints":2393,"distanceInMeters":1365971.501590356,"time":13,"lat":-0.2746706251885565,"lng":102.62537261231569},{"playerName":"HectorHTC","playerId":"57832f3322054780403ba592","roundScoreInPoints":2344,"distanceInMeters":1403860.2938548503,"time":30,"lat":-6.416806003712508,"lng":107.28914709841231},{"playerName":"EquisPY","playerId":"6039398f5cdb1b0001baf058","roundScoreInPoints":2510,"distanceInMeters":1277445.3325239138,"time":13,"lat":3.410199629496619,"lng":102.57321306643789},{"playerName":"carnarfi","playerId":"5ffc9e5f4a5efa00015dd50b","roundScoreInPoints":2469,"distanceInMeters":1308181.8009635587,"time":10,"lat":3.583770704519352,"lng":102.28313877822711},{"playerName":"Shark0s","playerId":"5be9cbd71f3cf81af810ab67","roundScoreInPoints":2616,"distanceInMeters":1200385.872331017,"time":27,"lat":2.007959989231763,"lng":103.47998143371194},{"playerName":"mat","playerId":"5f9329845f4b3600017951e5","roundScoreInPoints":2874,"distanceInMeters":1026432.8524966508,"time":20,"lat":-2.674818700099248,"lng":107.94668285988546},{"playerName":"Clara Hhh","playerId":"571802f3c974ed353ccf1bd6","roundScoreInPoints":1896,"distanceInMeters":1797255.7384539673,"time":23,"lat":16.503680830186475,"lng":103.32037781221459},{"playerName":"DJTonyRH","playerId":"60353d3eed952600012c0464","roundScoreInPoints":2590,"distanceInMeters":1218923.265060321,"time":26,"lat":11.529680324390855,"lng":122.33546808194507},{"playerName":"Luckylae","playerId":"605ba9ca9f11430001849351","roundScoreInPoints":72,"distanceInMeters":7869180.830195039,"time":30,"lat":-38.56703459715226,"lng":175.26363222546013},{"playerName":"dembelebalondeoro","playerId":"6058a96972a5a9000142195c","roundScoreInPoints":2285,"distanceInMeters":1451220.2502833044,"time":15,"lat":-1.094373275256522,"lng":102.14042930069701},{"playerName":"Anyelo Aldair Amaya Castro","playerId":"5ef940c95f12bd8244134bb2","roundScoreInPoints":2350,"distanceInMeters":1399186.672212397,"time":30,"lat":-4.05092501761672,"lng":104.59015981180556}],[{"playerName":"AxelBaxel","playerId":"5527cf44a3a64428d4b6edf9","roundScoreInPoints":4332,"distanceInMeters":265879.5646750964,"time":27,"lat":37.793520437268725,"lng":138.98930688329477},{"playerName":"HugoCL","playerId":"5e8609cb3d4b6a3cf8dcfc9c","roundScoreInPoints":4203,"distanceInMeters":321914.2029980684,"time":26,"lat":34.73688937389152,"lng":135.9266678395694},{"playerName":"emi_1312","playerId":"5f931ed7c00e2400014430c9","roundScoreInPoints":4403,"distanceInMeters":235798.1039615094,"time":22,"lat":35.37603819618488,"lng":136.76322563814267},{"playerName":"Gorka1311","playerId":"5a4e3f8057f1750a400a8050","roundScoreInPoints":4250,"distanceInMeters":301396.9435444894,"time":21,"lat":35.53643832148715,"lng":136.0384972027995},{"playerName":"tfl","playerId":"5783a7e0344dc34398cac4c4","roundScoreInPoints":4850,"distanceInMeters":56297.386993818,"time":26,"lat":35.86640744185482,"lng":139.66135732995645},{"playerName":"HectorHTC","playerId":"57832f3322054780403ba592","roundScoreInPoints":4535,"distanceInMeters":181124.0313166461,"time":30,"lat":35.371605277835926,"lng":137.36686394335356},{"playerName":"EquisPY","playerId":"6039398f5cdb1b0001baf058","roundScoreInPoints":4420,"distanceInMeters":228710.2161808208,"time":13,"lat":35.19792473310367,"lng":136.8585372108562},{"playerName":"carnarfi","playerId":"5ffc9e5f4a5efa00015dd50b","roundScoreInPoints":4293,"distanceInMeters":282765.6255915104,"time":18,"lat":35.09133509628976,"lng":136.27622481025662},{"playerName":"Shark0s","playerId":"5be9cbd71f3cf81af810ab67","roundScoreInPoints":4144,"distanceInMeters":348162.1373388844,"time":30,"lat":34.92025560688699,"lng":135.582946062782},{"playerName":"mat","playerId":"5f9329845f4b3600017951e5","roundScoreInPoints":4252,"distanceInMeters":300365.297526314,"time":12,"lat":34.97829015656369,"lng":136.1031033997166},{"playerName":"Clara Hhh","playerId":"571802f3c974ed353ccf1bd6","roundScoreInPoints":4673,"distanceInMeters":125376.0744474689,"time":24,"lat":35.05579171147681,"lng":138.05827620727752},{"playerName":"DJTonyRH","playerId":"60353d3eed952600012c0464","roundScoreInPoints":4697,"distanceInMeters":115803.0397622111,"time":30,"lat":36.20126975838799,"lng":138.51303164284775},{"playerName":"Luckylae","playerId":"605ba9ca9f11430001849351","roundScoreInPoints":4289,"distanceInMeters":284172.168792027,"time":15,"lat":37.976855214363496,"lng":139.32627803611388},{"playerName":"dembelebalondeoro","playerId":"6058a96972a5a9000142195c","roundScoreInPoints":4695,"distanceInMeters":116728.1925019422,"time":26,"lat":35.44104964635454,"lng":138.07606634142786},{"playerName":"Anyelo Aldair Amaya Castro","playerId":"5ef940c95f12bd8244134bb2","roundScoreInPoints":36,"distanceInMeters":9163032.746993434,"time":30,"lat":31.86197936412895,"lng":34.82249983854998}],[{"playerName":"AxelBaxel","playerId":"5527cf44a3a64428d4b6edf9","roundScoreInPoints":4273,"distanceInMeters":291090.8849514305,"time":30,"lat":66.15120517302441,"lng":27.750263849886267},{"playerName":"HugoCL","playerId":"5e8609cb3d4b6a3cf8dcfc9c","roundScoreInPoints":4510,"distanceInMeters":191264.2636535756,"time":18,"lat":63.451104528338234,"lng":24.76663252230443},{"playerName":"emi_1312","playerId":"5f931ed7c00e2400014430c9","roundScoreInPoints":4313,"distanceInMeters":273902.8641197312,"time":22,"lat":65.96529562766834,"lng":27.37616561840275},{"playerName":"Gorka1311","playerId":"5a4e3f8057f1750a400a8050","roundScoreInPoints":4669,"distanceInMeters":126894.6996507281,"time":11,"lat":64.57718446683934,"lng":27.435461061008926},{"playerName":"tfl","playerId":"5783a7e0344dc34398cac4c4","roundScoreInPoints":4481,"distanceInMeters":203256.0893913457,"time":28,"lat":62.420309069559174,"lng":25.46611294660312},{"playerName":"HectorHTC","playerId":"57832f3322054780403ba592","roundScoreInPoints":3024,"distanceInMeters":932279.6824679808,"time":29,"lat":62.68525987565678,"lng":10.104436977449911},{"playerName":"EquisPY","playerId":"6039398f5cdb1b0001baf058","roundScoreInPoints":4726,"distanceInMeters":104329.82712955,"time":12,"lat":64.2302084548805,"lng":27.124662246369937},{"playerName":"carnarfi","playerId":"5ffc9e5f4a5efa00015dd50b","roundScoreInPoints":4330,"distanceInMeters":266581.8097869298,"time":16,"lat":63.05703332769891,"lng":23.394818542253745},{"playerName":"Shark0s","playerId":"5be9cbd71f3cf81af810ab67","roundScoreInPoints":3964,"distanceInMeters":430293.6526304707,"time":17,"lat":67.35285159040467,"lng":26.771604663970663},{"playerName":"mat","playerId":"5f9329845f4b3600017951e5","roundScoreInPoints":2834,"distanceInMeters":1052550.0528333469,"time":18,"lat":61.17040640632549,"lng":8.773248922423353},{"playerName":"Clara Hhh","playerId":"571802f3c974ed353ccf1bd6","roundScoreInPoints":4575,"distanceInMeters":164621.9270381948,"time":14,"lat":64.02305886889198,"lng":25.43138762418073},{"playerName":"DJTonyRH","playerId":"60353d3eed952600012c0464","roundScoreInPoints":1661,"distanceInMeters":2042450.6214585644,"time":30,"lat":53.15147369170497,"lng":-0.8310864744125865},{"playerName":"Luckylae","playerId":"605ba9ca9f11430001849351","roundScoreInPoints":3749,"distanceInMeters":533892.4761506509,"time":15,"lat":65.64567161890317,"lng":18.514023254001245},{"playerName":"dembelebalondeoro","playerId":"6058a96972a5a9000142195c","roundScoreInPoints":164,"distanceInMeters":6330359.967642276,"time":29,"lat":54.43984405993373,"lng":-106.27327082410494},{"playerName":"Anyelo Aldair Amaya Castro","playerId":"5ef940c95f12bd8244134bb2","roundScoreInPoints":273,"distanceInMeters":5391354.066111271,"time":22,"lat":51.88599408244083,"lng":-70.1064297938416}],[{"playerName":"AxelBaxel","playerId":"5527cf44a3a64428d4b6edf9","roundScoreInPoints":4858,"distanceInMeters":53365.2754474645,"time":26,"lat":-37.91798653931817,"lng":175.41896854002573},{"playerName":"HugoCL","playerId":"5e8609cb3d4b6a3cf8dcfc9c","roundScoreInPoints":4622,"distanceInMeters":145835.1411414315,"time":22,"lat":-39.072497231529866,"lng":175.5249265313771},{"playerName":"emi_1312","playerId":"5f931ed7c00e2400014430c9","roundScoreInPoints":4421,"distanceInMeters":228305.2307968366,"time":23,"lat":-39.80039019945311,"lng":175.3272600965513},{"playerName":"Gorka1311","playerId":"5a4e3f8057f1750a400a8050","roundScoreInPoints":4176,"distanceInMeters":333790.9138737076,"time":25,"lat":-39.61584996169803,"lng":172.93203657958242},{"playerName":"tfl","playerId":"5783a7e0344dc34398cac4c4","roundScoreInPoints":4401,"distanceInMeters":236381.9988549106,"time":17,"lat":-39.921468553315606,"lng":175.61808554277314},{"playerName":"HectorHTC","playerId":"57832f3322054780403ba592","roundScoreInPoints":4150,"distanceInMeters":345380.152652196,"time":30,"lat":-40.88632568329603,"lng":175.38860485414068},{"playerName":"EquisPY","playerId":"6039398f5cdb1b0001baf058","roundScoreInPoints":1198,"distanceInMeters":2648845.7237071176,"time":18,"lat":-33.820082505253744,"lng":146.92847380931798},{"playerName":"carnarfi","playerId":"5ffc9e5f4a5efa00015dd50b","roundScoreInPoints":4785,"distanceInMeters":81594.3570219685,"time":30,"lat":-37.53873503286555,"lng":175.15622191537022},{"playerName":"Shark0s","playerId":"5be9cbd71f3cf81af810ab67","roundScoreInPoints":4337,"distanceInMeters":263458.632808639,"time":30,"lat":-40.18038437810608,"lng":175.77931790024383},{"playerName":"mat","playerId":"5f9329845f4b3600017951e5","roundScoreInPoints":4743,"distanceInMeters":97756.5231768312,"time":30,"lat":-38.63443309742533,"lng":175.5983298620364},{"playerName":"Clara Hhh","playerId":"571802f3c974ed353ccf1bd6","roundScoreInPoints":0,"distanceInMeters":18458050.677538462,"time":17,"lat":51.74104023200918,"lng":-1.8628585389436694},{"playerName":"DJTonyRH","playerId":"60353d3eed952600012c0464","roundScoreInPoints":1334,"distanceInMeters":2449568.8741360265,"time":30,"lat":-33.091335490237704,"lng":149.4995154919527},{"playerName":"Luckylae","playerId":"605ba9ca9f11430001849351","roundScoreInPoints":7,"distanceInMeters":12162408.933669923,"time":30,"lat":-27.862459248042708,"lng":23.70776629234689},{"playerName":"dembelebalondeoro","playerId":"6058a96972a5a9000142195c","roundScoreInPoints":0,"distanceInMeters":18204604.766537905,"time":30,"lat":54.04391520654078,"lng":-2.0152171574935664},{"playerName":"Anyelo Aldair Amaya Castro","playerId":"5ef940c95f12bd8244134bb2","roundScoreInPoints":0,"distanceInMeters":17296030.93089698,"time":30,"lat":60.9643556256923,"lng":8.592731248886615}]],"playerGames":[{"player":"AxelBaxel","playerId":"5527cf44a3a64428d4b6edf9","points":22038,"r1":{"points":3952,"time":11},"r2":{"points":4623,"time":12},"r3":{"points":4332,"time":27},"r4":{"points":4273,"time":30},"r5":{"points":4858,"time":26},"eliminatedInGame":null,"totalDistanceInMeters":1191562.6199160186,"totalTime":106,"pinUrl":"pin/90900c9cf45f33e8b4990f4a81fb8f65.png"},{"player":"HugoCL","playerId":"5e8609cb3d4b6a3cf8dcfc9c","points":20710,"r1":{"points":3168,"time":24},"r2":{"points":4207,"time":19},"r3":{"points":4203,"time":26},"r4":{"points":4510,"time":18},"r5":{"points":4622,"time":22},"eliminatedInGame":null,"totalDistanceInMeters":1825051.3590987292,"totalTime":110,"pinUrl":"pin/b9ef94b740e9e7b27865d3f11762906f.png"},{"player":"emi_1312","playerId":"5f931ed7c00e2400014430c9","points":20298,"r1":{"points":3073,"time":27},"r2":{"points":4088,"time":25},"r3":{"points":4403,"time":22},"r4":{"points":4313,"time":22},"r5":{"points":4421,"time":23},"eliminatedInGame":null,"totalDistanceInMeters":2013106.5190616224,"totalTime":119,"pinUrl":"pin/7c973b63b16fc0e1e54da798df26d107.png"},{"player":"Gorka1311","playerId":"5a4e3f8057f1750a400a8050","points":20127,"r1":{"points":3034,"time":17},"r2":{"points":3998,"time":15},"r3":{"points":4250,"time":21},"r4":{"points":4669,"time":11},"r5":{"points":4176,"time":25},"eliminatedInGame":null,"totalDistanceInMeters":2102661.2884339984,"totalTime":88,"pinUrl":"pin/b92e34dc5e27036bb6ebbfbdd35c3ba1.png"},{"player":"tfl","playerId":"5783a7e0344dc34398cac4c4","points":18747,"r1":{"points":2622,"time":30},"r2":{"points":2393,"time":13},"r3":{"points":4850,"time":26},"r4":{"points":4481,"time":28},"r5":{"points":4401,"time":17},"eliminatedInGame":null,"totalDistanceInMeters":3058459.768625724,"totalTime":113,"pinUrl":"pin/39012fab4f1396a8ab35336303bdc6c3.png"},{"player":"HectorHTC","playerId":"57832f3322054780403ba592","points":17961,"r1":{"points":3908,"time":27},"r2":{"points":2344,"time":30},"r3":{"points":4535,"time":30},"r4":{"points":3024,"time":29},"r5":{"points":4150,"time":30},"eliminatedInGame":null,"totalDistanceInMeters":3319304.1203616154,"totalTime":145,"pinUrl":"pin/1308ca85a16bb181136d5be40e914520.png"},{"player":"EquisPY","playerId":"6039398f5cdb1b0001baf058","points":16160,"r1":{"points":3306,"time":29},"r2":{"points":2510,"time":13},"r3":{"points":4420,"time":13},"r4":{"points":4726,"time":12},"r5":{"points":1198,"time":18},"eliminatedInGame":"-","totalDistanceInMeters":5026254.047467288,"totalTime":86,"pinUrl":"pin/452f068533d7f897c02fd51aadee1d93.png"},{"player":"carnarfi","playerId":"5ffc9e5f4a5efa00015dd50b","points":15953,"r1":{"points":76,"time":28},"r2":{"points":2469,"time":10},"r3":{"points":4293,"time":18},"r4":{"points":4330,"time":16},"r5":{"points":4785,"time":30},"eliminatedInGame":null,"totalDistanceInMeters":9701623.80820915,"totalTime":102,"pinUrl":"pin/d8a0eedf7fae6069582c99171764db28.png"},{"player":"Shark0s","playerId":"5be9cbd71f3cf81af810ab67","points":15158,"r1":{"points":97,"time":30},"r2":{"points":2616,"time":27},"r3":{"points":4144,"time":30},"r4":{"points":3964,"time":17},"r5":{"points":4337,"time":30},"eliminatedInGame":null,"totalDistanceInMeters":9554323.989662053,"totalTime":134,"pinUrl":"pin/b713e0e3e92745f87336894f59565483.png"},{"player":"mat","playerId":"5f9329845f4b3600017951e5","points":14753,"r1":{"points":50,"time":22},"r2":{"points":2874,"time":20},"r3":{"points":4252,"time":12},"r4":{"points":2834,"time":18},"r5":{"points":4743,"time":30},"eliminatedInGame":null,"totalDistanceInMeters":11009183.138149116,"totalTime":102,"pinUrl":"pin/6bbfdd40d3d338511d5537574b511729.png"},{"player":"Clara Hhh","playerId":"571802f3c974ed353ccf1bd6","points":11233,"r1":{"points":89,"time":22},"r2":{"points":1896,"time":23},"r3":{"points":4673,"time":24},"r4":{"points":4575,"time":14},"r5":{"points":0,"time":17},"eliminatedInGame":"-","totalDistanceInMeters":28013316.6517993,"totalTime":100,"pinUrl":"pin/7b99ea09f1236c687872252b03a8ad54.png"},{"player":"DJTonyRH","playerId":"60353d3eed952600012c0464","points":10286,"r1":{"points":4,"time":21},"r2":{"points":2590,"time":26},"r3":{"points":4697,"time":30},"r4":{"points":1661,"time":30},"r5":{"points":1334,"time":30},"eliminatedInGame":"1","totalDistanceInMeters":19057945.78110879,"totalTime":137,"pinUrl":""},{"player":"Luckylae","playerId":"605ba9ca9f11430001849351","points":8190,"r1":{"points":73,"time":16},"r2":{"points":72,"time":30},"r3":{"points":4289,"time":15},"r4":{"points":3749,"time":15},"r5":{"points":7,"time":30},"eliminatedInGame":"2","totalDistanceInMeters":28690295.112027973,"totalTime":106,"pinUrl":"pin/9650e5d43f876e016bc4abbd1a04de2b.png"},{"player":"dembelebalondeoro","playerId":"6058a96972a5a9000142195c","points":7862,"r1":{"points":718,"time":23},"r2":{"points":2285,"time":15},"r3":{"points":4695,"time":26},"r4":{"points":164,"time":29},"r5":{"points":0,"time":30},"eliminatedInGame":"1","totalDistanceInMeters":29700452.22736918,"totalTime":124,"pinUrl":"pin/7f79982ae37d352b5fc455626c5397b7.png"},{"player":"Anyelo Aldair Amaya Castro","playerId":"5ef940c95f12bd8244134bb2","points":2833,"r1":{"points":174,"time":30},"r2":{"points":2350,"time":30},"r3":{"points":36,"time":30},"r4":{"points":273,"time":22},"r5":{"points":0,"time":30},"eliminatedInGame":"2","totalDistanceInMeters":39469468.88586554,"totalTime":141,"pinUrl":""}],"answers":[{"lat":49.2809511031255,"lng":-99.43050247134613,"countryCode":"CA","countryName":"Canada"},{"lat":4.248290850155575,"lng":114.0567705722011,"countryCode":"MY","countryName":"Malaysia"},{"lat":35.42141428883406,"lng":139.3641987747071,"countryCode":"JP","countryName":"Japan"},{"lat":63.55922670321573,"lng":28.615265656534348,"countryCode":"FI","countryName":"Finland"},{"lat":-37.81804617388814,"lng":176.0135837527753,"countryCode":"NZ","countryName":"New Zealand"}],"mapName":"A Diverse World","gameNumber":2,"gameUrl":"https://www.geoguessr.com/results/T1hRBNChLjZiuiUA","gameId":"T1hRBNChLjZiuiUA","gameDescription":"30 sec. No move","playedWithEliminations":true,"forbidMoving":true,"forbidRotating":false,"forbidZooming":false,"timeLimit":30},{"allGuesses":[[{"playerName":"Shark0s","playerId":"5be9cbd71f3cf81af810ab67","roundScoreInPoints":3890,"distanceInMeters":465162.2157510126,"time":30,"lat":38.881713373209294,"lng":27.200919945466637},{"playerName":"mat","playerId":"5f9329845f4b3600017951e5","roundScoreInPoints":1005,"distanceInMeters":2973444.648608961,"time":16,"lat":37.91181129564588,"lng":-1.6974072423940534},{"playerName":"HectorHTC","playerId":"57832f3322054780403ba592","roundScoreInPoints":1032,"distanceInMeters":2924651.1903288877,"time":29,"lat":39.87030389176531,"lng":-1.5085022530242576},{"playerName":"carnarfi","playerId":"5ffc9e5f4a5efa00015dd50b","roundScoreInPoints":1011,"distanceInMeters":2962021.7882272964,"time":21,"lat":61.87165982997764,"lng":13.646524513572047},{"playerName":"emi_1312","playerId":"5f931ed7c00e2400014430c9","roundScoreInPoints":1003,"distanceInMeters":2977959.867032582,"time":26,"lat":40.1069005528931,"lng":-2.1737939198677054},{"playerName":"AxelBaxel","playerId":"5527cf44a3a64428d4b6edf9","roundScoreInPoints":104,"distanceInMeters":7180629.407949403,"time":9,"lat":-26.696935159090106,"lng":31.586326523174534},{"playerName":"Anyelo Aldair Amaya Castro","playerId":"5ef940c95f12bd8244134bb2","roundScoreInPoints":979,"distanceInMeters":3023275.146915056,"time":30,"lat":39.41822662904517,"lng":-2.5944121634884065},{"playerName":"HugoCL","playerId":"5e8609cb3d4b6a3cf8dcfc9c","roundScoreInPoints":1070,"distanceInMeters":2856878.4733769237,"time":24,"lat":41.34238423036781,"lng":-0.871328507156528},{"playerName":"Luckylae","playerId":"605ba9ca9f11430001849351","roundScoreInPoints":93,"distanceInMeters":7389671.441641669,"time":30,"lat":-28.092543640623152,"lng":23.79549405402158},{"playerName":"tfl","playerId":"5783a7e0344dc34398cac4c4","roundScoreInPoints":103,"distanceInMeters":7193999.982980256,"time":30,"lat":-26.655586575868263,"lng":27.445809600707946},{"playerName":"Gorka1311","playerId":"5a4e3f8057f1750a400a8050","roundScoreInPoints":8,"distanceInMeters":11823147.256034276,"time":23,"lat":21.254215826896573,"lng":-100.83008197601869},{"playerName":"DJTonyRH","playerId":"60353d3eed952600012c0464","roundScoreInPoints":0,"distanceInMeters":5359003.7407178935,"time":30,"lat":0,"lng":0},{"playerName":"dembelebalondeoro","playerId":"6058a96972a5a9000142195c","roundScoreInPoints":9,"distanceInMeters":11813054.758367945,"time":21,"lat":-31.38713215696339,"lng":118.96652128234996}],[{"playerName":"Shark0s","playerId":"5be9cbd71f3cf81af810ab67","roundScoreInPoints":4216,"distanceInMeters":316187.1628987052,"time":23,"lat":61.113408531000076,"lng":15.047553053873685},{"playerName":"mat","playerId":"5f9329845f4b3600017951e5","roundScoreInPoints":4639,"distanceInMeters":138956.7000428244,"time":20,"lat":57.791277869009626,"lng":14.392204164947149},{"playerName":"HectorHTC","playerId":"57832f3322054780403ba592","roundScoreInPoints":3963,"distanceInMeters":430765.8351665674,"time":27,"lat":62.37811042255399,"lng":13.92993426109685},{"playerName":"carnarfi","playerId":"5ffc9e5f4a5efa00015dd50b","roundScoreInPoints":4062,"distanceInMeters":385192.8933096993,"time":8,"lat":61.850538772602846,"lng":14.748803878010563},{"playerName":"emi_1312","playerId":"5f931ed7c00e2400014430c9","roundScoreInPoints":4343,"distanceInMeters":260964.9904817608,"time":19,"lat":60.52708263640453,"lng":15.075934385713595},{"playerName":"AxelBaxel","playerId":"5527cf44a3a64428d4b6edf9","roundScoreInPoints":4643,"distanceInMeters":137376.4192951048,"time":7,"lat":58.119234783679076,"lng":14.726922896075791},{"playerName":"Anyelo Aldair Amaya Castro","playerId":"5ef940c95f12bd8244134bb2","roundScoreInPoints":4184,"distanceInMeters":330428.5264719992,"time":30,"lat":60.41858923058599,"lng":17.110991400283353},{"playerName":"HugoCL","playerId":"5e8609cb3d4b6a3cf8dcfc9c","roundScoreInPoints":4353,"distanceInMeters":256982.4223724396,"time":11,"lat":60.41638511059592,"lng":15.25977691541053},{"playerName":"Luckylae","playerId":"605ba9ca9f11430001849351","roundScoreInPoints":3223,"distanceInMeters":814068.2985241376,"time":16,"lat":56.99411885113008,"lng":25.968615733198646},{"playerName":"tfl","playerId":"5783a7e0344dc34398cac4c4","roundScoreInPoints":4503,"distanceInMeters":194130.7100508932,"time":21,"lat":59.11324174071636,"lng":15.736089261496545},{"playerName":"Gorka1311","playerId":"5a4e3f8057f1750a400a8050","roundScoreInPoints":4151,"distanceInMeters":345073.7376169318,"time":9,"lat":61.581982930922486,"lng":11.067474104461809},{"playerName":"DJTonyRH","playerId":"60353d3eed952600012c0464","roundScoreInPoints":3250,"distanceInMeters":798693.6073192657,"time":23,"lat":56.734048568200585,"lng":25.53627486874415},{"playerName":"dembelebalondeoro","playerId":"6058a96972a5a9000142195c","roundScoreInPoints":4007,"distanceInMeters":410278.9939006508,"time":24,"lat":61.56945981224938,"lng":16.83183604265014}],[{"playerName":"Shark0s","playerId":"5be9cbd71f3cf81af810ab67","roundScoreInPoints":4800,"distanceInMeters":75816.3568592761,"time":28,"lat":50.70237535399452,"lng":4.744303783654686},{"playerName":"mat","playerId":"5f9329845f4b3600017951e5","roundScoreInPoints":4646,"distanceInMeters":135933.2317806999,"time":30,"lat":50.23529264572373,"lng":4.243664811773851},{"playerName":"HectorHTC","playerId":"57832f3322054780403ba592","roundScoreInPoints":4893,"distanceInMeters":40002.839537172,"time":30,"lat":50.709487544092134,"lng":5.742371860397402},{"playerName":"carnarfi","playerId":"5ffc9e5f4a5efa00015dd50b","roundScoreInPoints":4840,"distanceInMeters":60178.093306977,"time":28,"lat":50.589213125391076,"lng":5.251977700388693},{"playerName":"emi_1312","playerId":"5f931ed7c00e2400014430c9","roundScoreInPoints":4072,"distanceInMeters":380387.1685343222,"time":30,"lat":51.93220678029601,"lng":0.3418719999932023},{"playerName":"AxelBaxel","playerId":"5527cf44a3a64428d4b6edf9","roundScoreInPoints":4830,"distanceInMeters":63930.1299792471,"time":15,"lat":50.794160371820006,"lng":4.854824429007465},{"playerName":"Anyelo Aldair Amaya Castro","playerId":"5ef940c95f12bd8244134bb2","roundScoreInPoints":3822,"distanceInMeters":497998.0228180862,"time":30,"lat":52.19735695258115,"lng":-1.3250935144263898},{"playerName":"HugoCL","playerId":"5e8609cb3d4b6a3cf8dcfc9c","roundScoreInPoints":2598,"distanceInMeters":1213485.5787749744,"time":30,"lat":46.12222878219263,"lng":20.414925607652567},{"playerName":"Luckylae","playerId":"605ba9ca9f11430001849351","roundScoreInPoints":4151,"distanceInMeters":344774.08334422,"time":21,"lat":50.34633508087627,"lng":10.422642663512192},{"playerName":"tfl","playerId":"5783a7e0344dc34398cac4c4","roundScoreInPoints":186,"distanceInMeters":6102643.755792796,"time":30,"lat":40.03729634120792,"lng":-75.3890590235889},{"playerName":"Gorka1311","playerId":"5a4e3f8057f1750a400a8050","roundScoreInPoints":0,"distanceInMeters":18347374.29584736,"time":30,"lat":-37.7761828098469,"lng":175.8323556315368},{"playerName":"DJTonyRH","playerId":"60353d3eed952600012c0464","roundScoreInPoints":316,"distanceInMeters":5118333.0593065135,"time":30,"lat":45.899402125603075,"lng":-66.26725041605319},{"playerName":"dembelebalondeoro","playerId":"6058a96972a5a9000142195c","roundScoreInPoints":44,"distanceInMeters":8763930.194345174,"time":28,"lat":36.25660723832815,"lng":127.33047434276472}],[{"playerName":"Shark0s","playerId":"5be9cbd71f3cf81af810ab67","roundScoreInPoints":4313,"distanceInMeters":273779.1418521434,"time":30,"lat":45.81107422267478,"lng":8.553958696663187},{"playerName":"mat","playerId":"5f9329845f4b3600017951e5","roundScoreInPoints":4577,"distanceInMeters":163678.4805897334,"time":25,"lat":46.17071339828071,"lng":9.893909942283145},{"playerName":"HectorHTC","playerId":"57832f3322054780403ba592","roundScoreInPoints":4566,"distanceInMeters":168201.5057646056,"time":30,"lat":46.828427392678,"lng":9.859011902864413},{"playerName":"carnarfi","playerId":"5ffc9e5f4a5efa00015dd50b","roundScoreInPoints":4489,"distanceInMeters":199704.9250009024,"time":30,"lat":46.257005378520724,"lng":9.400265074351637},{"playerName":"emi_1312","playerId":"5f931ed7c00e2400014430c9","roundScoreInPoints":4858,"distanceInMeters":53276.4312314049,"time":25,"lat":46.68647460763477,"lng":11.390150021597094},{"playerName":"AxelBaxel","playerId":"5527cf44a3a64428d4b6edf9","roundScoreInPoints":4509,"distanceInMeters":191722.1123312997,"time":23,"lat":45.93549470086142,"lng":9.60733042768419},{"playerName":"Anyelo Aldair Amaya Castro","playerId":"5ef940c95f12bd8244134bb2","roundScoreInPoints":4843,"distanceInMeters":59226.2303276668,"time":30,"lat":46.20669897282985,"lng":11.295912444104488},{"playerName":"HugoCL","playerId":"5e8609cb3d4b6a3cf8dcfc9c","roundScoreInPoints":4289,"distanceInMeters":284404.1731597966,"time":17,"lat":45.87769378043182,"lng":8.38626298916075},{"playerName":"Luckylae","playerId":"605ba9ca9f11430001849351","roundScoreInPoints":4176,"distanceInMeters":333885.8435238478,"time":30,"lat":47.00849605828322,"lng":7.6866308775938705},{"playerName":"tfl","playerId":"5783a7e0344dc34398cac4c4","roundScoreInPoints":4515,"distanceInMeters":189236.9712157947,"time":30,"lat":46.21400996525338,"lng":9.545963009339687},{"playerName":"Gorka1311","playerId":"5a4e3f8057f1750a400a8050","roundScoreInPoints":4132,"distanceInMeters":353426.6746932632,"time":30,"lat":45.74727491758261,"lng":7.515022990780471},{"playerName":"DJTonyRH","playerId":"60353d3eed952600012c0464","roundScoreInPoints":4918,"distanceInMeters":30796.7516431058,"time":28,"lat":46.38101010596768,"lng":12.380755476253643},{"playerName":"dembelebalondeoro","playerId":"6058a96972a5a9000142195c","roundScoreInPoints":4447,"distanceInMeters":217129.0486200333,"time":30,"lat":44.740977113229235,"lng":10.615452992409619}],[{"playerName":"Shark0s","playerId":"5be9cbd71f3cf81af810ab67","roundScoreInPoints":218,"distanceInMeters":5805031.320603928,"time":30,"lat":58.28253363048767,"lng":-4.270448419532045},{"playerName":"mat","playerId":"5f9329845f4b3600017951e5","roundScoreInPoints":292,"distanceInMeters":5265986.810097031,"time":14,"lat":68.4601390234373,"lng":18.328708164261798},{"playerName":"HectorHTC","playerId":"57832f3322054780403ba592","roundScoreInPoints":195,"distanceInMeters":6008422.3808243815,"time":26,"lat":60.47763826019919,"lng":13.190158287226724},{"playerName":"carnarfi","playerId":"5ffc9e5f4a5efa00015dd50b","roundScoreInPoints":94,"distanceInMeters":7356702.611796802,"time":25,"lat":46.93692920185868,"lng":10.396402920537753},{"playerName":"emi_1312","playerId":"5f931ed7c00e2400014430c9","roundScoreInPoints":74,"distanceInMeters":7818227.458432954,"time":30,"lat":42.18781020274521,"lng":9.06300448879216},{"playerName":"AxelBaxel","playerId":"5527cf44a3a64428d4b6edf9","roundScoreInPoints":175,"distanceInMeters":6211817.1729279645,"time":16,"lat":54.484426293812334,"lng":-3.0587192039860156},{"playerName":"Anyelo Aldair Amaya Castro","playerId":"5ef940c95f12bd8244134bb2","roundScoreInPoints":241,"distanceInMeters":5623127.619705719,"time":30,"lat":62.58557162896458,"lng":5.137618507538386},{"playerName":"HugoCL","playerId":"5e8609cb3d4b6a3cf8dcfc9c","roundScoreInPoints":55,"distanceInMeters":8369827.755863685,"time":16,"lat":39.85495806918495,"lng":21.531838483316946},{"playerName":"Luckylae","playerId":"605ba9ca9f11430001849351","roundScoreInPoints":207,"distanceInMeters":5906582.594197654,"time":27,"lat":61.560529512919295,"lng":13.731098828816357},{"playerName":"tfl","playerId":"5783a7e0344dc34398cac4c4","roundScoreInPoints":297,"distanceInMeters":5233284.034868076,"time":11,"lat":68.61905520274149,"lng":17.21062713809289},{"playerName":"Gorka1311","playerId":"5a4e3f8057f1750a400a8050","roundScoreInPoints":306,"distanceInMeters":5177002.264514274,"time":9,"lat":69.83387243204872,"lng":22.515786495321287},{"playerName":"DJTonyRH","playerId":"60353d3eed952600012c0464","roundScoreInPoints":94,"distanceInMeters":7374440.720163918,"time":30,"lat":41.99805504734685,"lng":-5.524581557869079},{"playerName":"dembelebalondeoro","playerId":"6058a96972a5a9000142195c","roundScoreInPoints":41,"distanceInMeters":8890044.483436175,"time":28,"lat":-3.80527055411909,"lng":-68.26460363585363}]],"playerGames":[{"player":"Shark0s","playerId":"5be9cbd71f3cf81af810ab67","points":17437,"r1":{"points":3890,"time":30},"r2":{"points":4216,"time":23},"r3":{"points":4800,"time":28},"r4":{"points":4313,"time":30},"r5":{"points":218,"time":30},"eliminatedInGame":null,"totalDistanceInMeters":6935976.197965065,"totalTime":141,"pinUrl":"pin/b713e0e3e92745f87336894f59565483.png"},{"player":"mat","playerId":"5f9329845f4b3600017951e5","points":15159,"r1":{"points":1005,"time":16},"r2":{"points":4639,"time":20},"r3":{"points":4646,"time":30},"r4":{"points":4577,"time":25},"r5":{"points":292,"time":14},"eliminatedInGame":null,"totalDistanceInMeters":8677999.87111925,"totalTime":104,"pinUrl":"pin/6bbfdd40d3d338511d5537574b511729.png"},{"player":"HectorHTC","playerId":"57832f3322054780403ba592","points":14649,"r1":{"points":1032,"time":29},"r2":{"points":3963,"time":27},"r3":{"points":4893,"time":30},"r4":{"points":4566,"time":30},"r5":{"points":195,"time":26},"eliminatedInGame":null,"totalDistanceInMeters":9572043.751621615,"totalTime":142,"pinUrl":"pin/1308ca85a16bb181136d5be40e914520.png"},{"player":"carnarfi","playerId":"5ffc9e5f4a5efa00015dd50b","points":14496,"r1":{"points":1011,"time":21},"r2":{"points":4062,"time":8},"r3":{"points":4840,"time":28},"r4":{"points":4489,"time":30},"r5":{"points":94,"time":25},"eliminatedInGame":null,"totalDistanceInMeters":10963800.311641676,"totalTime":112,"pinUrl":"pin/d8a0eedf7fae6069582c99171764db28.png"},{"player":"emi_1312","playerId":"5f931ed7c00e2400014430c9","points":14350,"r1":{"points":1003,"time":26},"r2":{"points":4343,"time":19},"r3":{"points":4072,"time":30},"r4":{"points":4858,"time":25},"r5":{"points":74,"time":30},"eliminatedInGame":null,"totalDistanceInMeters":11490815.915713023,"totalTime":130,"pinUrl":"pin/7c973b63b16fc0e1e54da798df26d107.png"},{"player":"AxelBaxel","playerId":"5527cf44a3a64428d4b6edf9","points":14261,"r1":{"points":104,"time":9},"r2":{"points":4643,"time":7},"r3":{"points":4830,"time":15},"r4":{"points":4509,"time":23},"r5":{"points":175,"time":16},"eliminatedInGame":null,"totalDistanceInMeters":13785475.24248302,"totalTime":70,"pinUrl":"pin/90900c9cf45f33e8b4990f4a81fb8f65.png"},{"player":"Anyelo Aldair Amaya Castro","playerId":"5ef940c95f12bd8244134bb2","points":14069,"r1":{"points":979,"time":30},"r2":{"points":4184,"time":30},"r3":{"points":3822,"time":30},"r4":{"points":4843,"time":30},"r5":{"points":241,"time":30},"eliminatedInGame":null,"totalDistanceInMeters":9534055.546238527,"totalTime":150,"pinUrl":""},{"player":"HugoCL","playerId":"5e8609cb3d4b6a3cf8dcfc9c","points":12365,"r1":{"points":1070,"time":24},"r2":{"points":4353,"time":11},"r3":{"points":2598,"time":30},"r4":{"points":4289,"time":17},"r5":{"points":55,"time":16},"eliminatedInGame":null,"totalDistanceInMeters":12981578.40354782,"totalTime":98,"pinUrl":"pin/b9ef94b740e9e7b27865d3f11762906f.png"},{"player":"Luckylae","playerId":"605ba9ca9f11430001849351","points":11850,"r1":{"points":93,"time":30},"r2":{"points":3223,"time":16},"r3":{"points":4151,"time":21},"r4":{"points":4176,"time":30},"r5":{"points":207,"time":27},"eliminatedInGame":null,"totalDistanceInMeters":14788982.261231527,"totalTime":124,"pinUrl":"pin/9650e5d43f876e016bc4abbd1a04de2b.png"},{"player":"tfl","playerId":"5783a7e0344dc34398cac4c4","points":9604,"r1":{"points":103,"time":30},"r2":{"points":4503,"time":21},"r3":{"points":186,"time":30},"r4":{"points":4515,"time":30},"r5":{"points":297,"time":11},"eliminatedInGame":null,"totalDistanceInMeters":18913295.454907812,"totalTime":122,"pinUrl":"pin/39012fab4f1396a8ab35336303bdc6c3.png"},{"player":"Gorka1311","playerId":"5a4e3f8057f1750a400a8050","points":8597,"r1":{"points":8,"time":23},"r2":{"points":4151,"time":9},"r3":{"points":0,"time":30},"r4":{"points":4132,"time":30},"r5":{"points":306,"time":9},"eliminatedInGame":null,"totalDistanceInMeters":36046024.22870611,"totalTime":101,"pinUrl":"pin/b92e34dc5e27036bb6ebbfbdd35c3ba1.png"},{"player":"DJTonyRH","playerId":"60353d3eed952600012c0464","points":8578,"r1":{"points":0,"time":30},"r2":{"points":3250,"time":23},"r3":{"points":316,"time":30},"r4":{"points":4918,"time":28},"r5":{"points":94,"time":30},"eliminatedInGame":"1","totalDistanceInMeters":18681267.879150696,"totalTime":141,"pinUrl":""},{"player":"dembelebalondeoro","playerId":"6058a96972a5a9000142195c","points":8548,"r1":{"points":9,"time":21},"r2":{"points":4007,"time":24},"r3":{"points":44,"time":28},"r4":{"points":4447,"time":30},"r5":{"points":41,"time":28},"eliminatedInGame":"1","totalDistanceInMeters":30094437.47866998,"totalTime":132,"pinUrl":"pin/7f79982ae37d352b5fc455626c5397b7.png"}],"answers":[{"lat":37.87570756402593,"lng":32.38155364090994,"countryCode":"TR","countryName":"Turkey"},{"lat":58.56566928192004,"lng":12.531873154600362,"countryCode":"SE","countryName":"Sweden"},{"lat":51.06539042687729,"lng":5.659150171349324,"countryCode":"BE","countryName":"Belgium"},{"lat":46.44097497026722,"lng":11.988586673139366,"countryCode":"IT","countryName":"Italy"},{"lat":62.01942,"lng":-128.39948,"countryCode":"CA","countryName":"Canada"}],"mapName":"A Diverse World","gameNumber":1,"gameUrl":"https://www.geoguessr.com/results/5CAYblgRfDoiqKaS","gameId":"5CAYblgRfDoiqKaS","gameDescription":"30 sec. No move","playedWithEliminations":true,"forbidMoving":true,"forbidRotating":false,"forbidZooming":false,"timeLimit":30}]}