{"nickname":"treatment","startTimeUtc":"2021-07-05T21:45:57.3393358Z","tournament":{"players":[{"playerId":"5e81caa3d51dd62ccc447f85","playerName":"Dadge City","totalPoints":18071,"games":[{"gamePoints":18071}]},{"playerId":"5e8609cb3d4b6a3cf8dcfc9c","playerName":"HugoCL","totalPoints":17520,"games":[{"gamePoints":17520}]},{"playerId":"59dba5865d2de4db803703fc","playerName":"Feliz cumplea\u00F1os Shark0s","totalPoints":16997,"games":[{"gamePoints":16997}]},{"playerId":"56a0744b93a14639dc49f6ec","playerName":"Manumalada","totalPoints":16324,"games":[{"gamePoints":16324}]},{"playerId":"5be9cbd71f3cf81af810ab67","playerName":"Shark0s","totalPoints":15981,"games":[{"gamePoints":15981}]},{"playerId":"5eea5f1162df1243a0cdd8e4","playerName":"Vell","totalPoints":15689,"games":[{"gamePoints":15689}]},{"playerId":"5f931ed7c00e2400014430c9","playerName":"emi_1312","totalPoints":15578,"games":[{"gamePoints":15578}]},{"playerId":"5a4e3f8057f1750a400a8050","playerName":"\uD83D\uDC8B \uD83D\uDC8B \uD83D\uDC8B \uD83D\uDC8B","totalPoints":14393,"games":[{"gamePoints":14393}]},{"playerId":"5f03b9a15b064d075036b8a4","playerName":"Patagonia TV","totalPoints":12967,"games":[{"gamePoints":12967}]},{"playerId":"5f60e5f1f0ded50001af4007","playerName":"Flop","totalPoints":10812,"games":[{"gamePoints":10812}]},{"playerId":"60d6240f548abb000175df09","playerName":"Eldelsur","totalPoints":8090,"games":[{"gamePoints":8090}]},{"playerId":"6034d9d899166a0001e87efc","playerName":"Marimil_","totalPoints":7646,"games":[{"gamePoints":7646}]}]},"games":[{"allGuesses":[[{"playerName":"Dadge City","playerId":"5e81caa3d51dd62ccc447f85","roundScoreInPoints":3210,"distanceInMeters":673923.1133907437,"time":34,"lat":66.09055957108974,"lng":-18.046333203361378},{"playerName":"HugoCL","playerId":"5e8609cb3d4b6a3cf8dcfc9c","roundScoreInPoints":4981,"distanceInMeters":5717.8060401931,"time":40,"lat":62.30523127847577,"lng":-6.996489108108643},{"playerName":"Feliz cumplea\u00F1os Shark0s","playerId":"59dba5865d2de4db803703fc","roundScoreInPoints":3486,"distanceInMeters":548605.8420508327,"time":38,"lat":57.64966237691427,"lng":-3.908464027844502},{"playerName":"Manumalada","playerId":"56a0744b93a14639dc49f6ec","roundScoreInPoints":2553,"distanceInMeters":1022405.9429491782,"time":40,"lat":66.03888496754868,"lng":12.324693659459873},{"playerName":"Shark0s","playerId":"5be9cbd71f3cf81af810ab67","roundScoreInPoints":3290,"distanceInMeters":636378.5110691848,"time":32,"lat":66.51574167905345,"lng":-16.15046280409058},{"playerName":"Vell","playerId":"5eea5f1162df1243a0cdd8e4","roundScoreInPoints":0,"distanceInMeters":6955176.69147939,"time":40,"lat":0,"lng":0},{"playerName":"emi_1312","playerId":"5f931ed7c00e2400014430c9","roundScoreInPoints":2819,"distanceInMeters":871577.2630119784,"time":37,"lat":66.4589227746674,"lng":-22.586483155458893},{"playerName":"\uD83D\uDC8B \uD83D\uDC8B \uD83D\uDC8B \uD83D\uDC8B","playerId":"5a4e3f8057f1750a400a8050","roundScoreInPoints":3286,"distanceInMeters":638477.0439264671,"time":17,"lat":64.70589841952469,"lng":-18.839836945224683},{"playerName":"Patagonia TV","playerId":"5f03b9a15b064d075036b8a4","roundScoreInPoints":4,"distanceInMeters":10989600.823746065,"time":28,"lat":-34.19021530373305,"lng":19.32989565940501},{"playerName":"Flop","playerId":"5f60e5f1f0ded50001af4007","roundScoreInPoints":1,"distanceInMeters":13945812.191275554,"time":20,"lat":-53.76628449897801,"lng":-67.71136820829616},{"playerName":"Eldelsur","playerId":"60d6240f548abb000175df09","roundScoreInPoints":2831,"distanceInMeters":865220.1516846711,"time":38,"lat":66.38528858013615,"lng":-22.513089161266535},{"playerName":"Marimil_","playerId":"6034d9d899166a0001e87efc","roundScoreInPoints":2347,"distanceInMeters":1149997.523927721,"time":26,"lat":70.70418419603807,"lng":-22.566530957705435}],[{"playerName":"Dadge City","playerId":"5e81caa3d51dd62ccc447f85","roundScoreInPoints":3217,"distanceInMeters":670523.7886163609,"time":40,"lat":-31.187664897628817,"lng":151.62620689290566},{"playerName":"HugoCL","playerId":"5e8609cb3d4b6a3cf8dcfc9c","roundScoreInPoints":1744,"distanceInMeters":1601618.1426685327,"time":20,"lat":-35.08670469837175,"lng":140.0953654070757},{"playerName":"Feliz cumplea\u00F1os Shark0s","playerId":"59dba5865d2de4db803703fc","roundScoreInPoints":1895,"distanceInMeters":1476013.8411154824,"time":20,"lat":-36.91741987225183,"lng":144.95652071344716},{"playerName":"Manumalada","playerId":"56a0744b93a14639dc49f6ec","roundScoreInPoints":1567,"distanceInMeters":1764637.4205939323,"time":40,"lat":-37.539531846246355,"lng":140.509812451832},{"playerName":"Shark0s","playerId":"5be9cbd71f3cf81af810ab67","roundScoreInPoints":1682,"distanceInMeters":1656625.5784874521,"time":26,"lat":-36.76763779902748,"lng":141.2559175029544},{"playerName":"Vell","playerId":"5eea5f1162df1243a0cdd8e4","roundScoreInPoints":4212,"distanceInMeters":260978.366357936,"time":21,"lat":-23.6056321328842,"lng":150.31050320224347},{"playerName":"emi_1312","playerId":"5f931ed7c00e2400014430c9","roundScoreInPoints":479,"distanceInMeters":3568431.0115655665,"time":34,"lat":-31.888225521869057,"lng":116.3225308088949},{"playerName":"\uD83D\uDC8B \uD83D\uDC8B \uD83D\uDC8B \uD83D\uDC8B","playerId":"5a4e3f8057f1750a400a8050","roundScoreInPoints":480,"distanceInMeters":3563571.9990937044,"time":20,"lat":-34.63935973751159,"lng":116.66904744098036},{"playerName":"Patagonia TV","playerId":"5f03b9a15b064d075036b8a4","roundScoreInPoints":837,"distanceInMeters":2718861.5902148723,"time":33,"lat":-44.81771115907844,"lng":170.25216958554654},{"playerName":"Flop","playerId":"5f60e5f1f0ded50001af4007","roundScoreInPoints":2839,"distanceInMeters":860648.8587649754,"time":17,"lat":-19.303270240850594,"lng":146.7761688605828},{"playerName":"Eldelsur","playerId":"60d6240f548abb000175df09","roundScoreInPoints":0,"distanceInMeters":15922575.638575405,"time":40,"lat":0,"lng":0},{"playerName":"Marimil_","playerId":"6034d9d899166a0001e87efc","roundScoreInPoints":834,"distanceInMeters":2723641.8479236723,"time":40,"lat":-39.61539975875115,"lng":175.84649267156294}],[{"playerName":"Dadge City","playerId":"5e81caa3d51dd62ccc447f85","roundScoreInPoints":2399,"distanceInMeters":1116964.5147604463,"time":35,"lat":-27.420587968038614,"lng":-58.85004606578553},{"playerName":"HugoCL","playerId":"5e8609cb3d4b6a3cf8dcfc9c","roundScoreInPoints":3184,"distanceInMeters":686585.6378746971,"time":11,"lat":-33.35077289821559,"lng":-55.39698206816277},{"playerName":"Feliz cumplea\u00F1os Shark0s","playerId":"59dba5865d2de4db803703fc","roundScoreInPoints":3306,"distanceInMeters":629104.4173102673,"time":15,"lat":-33.2919590721046,"lng":-56.31412535822662},{"playerName":"Manumalada","playerId":"56a0744b93a14639dc49f6ec","roundScoreInPoints":4373,"distanceInMeters":203848.845512876,"time":29,"lat":-35.45098794168649,"lng":-60.878781250749554},{"playerName":"Shark0s","playerId":"5be9cbd71f3cf81af810ab67","roundScoreInPoints":4034,"distanceInMeters":326645.2897278378,"time":35,"lat":-34.523973548830426,"lng":-59.93376181588161},{"playerName":"Vell","playerId":"5eea5f1162df1243a0cdd8e4","roundScoreInPoints":3204,"distanceInMeters":676963.2093822844,"time":23,"lat":-33.02024228593042,"lng":-55.910520089867816},{"playerName":"emi_1312","playerId":"5f931ed7c00e2400014430c9","roundScoreInPoints":3605,"distanceInMeters":497444.4632081677,"time":33,"lat":-32.954915829881145,"lng":-59.76465570041234},{"playerName":"\uD83D\uDC8B \uD83D\uDC8B \uD83D\uDC8B \uD83D\uDC8B","playerId":"5a4e3f8057f1750a400a8050","roundScoreInPoints":3155,"distanceInMeters":700105.2546411796,"time":10,"lat":-32.59497683804923,"lng":-56.095339357563475},{"playerName":"Patagonia TV","playerId":"5f03b9a15b064d075036b8a4","roundScoreInPoints":4492,"distanceInMeters":162931.2214317052,"time":18,"lat":-36.007725259946554,"lng":-60.307604080407835},{"playerName":"Flop","playerId":"5f60e5f1f0ded50001af4007","roundScoreInPoints":3274,"distanceInMeters":643933.7674702198,"time":11,"lat":-32.88205532407908,"lng":-56.621851241889715},{"playerName":"Eldelsur","playerId":"60d6240f548abb000175df09","roundScoreInPoints":1,"distanceInMeters":12462707.817018189,"time":34,"lat":46.162074414372825,"lng":22.410444441256168},{"playerName":"Marimil_","playerId":"6034d9d899166a0001e87efc","roundScoreInPoints":1,"distanceInMeters":12616319.488559818,"time":29,"lat":44.754898521729125,"lng":25.88877164207298}],[{"playerName":"Dadge City","playerId":"5e81caa3d51dd62ccc447f85","roundScoreInPoints":4665,"distanceInMeters":105529.2931297927,"time":40,"lat":58.09075255490626,"lng":12.772658977688595},{"playerName":"HugoCL","playerId":"5e8609cb3d4b6a3cf8dcfc9c","roundScoreInPoints":4568,"distanceInMeters":137559.5576211335,"time":17,"lat":59.43784105565488,"lng":15.401039607805851},{"playerName":"Feliz cumplea\u00F1os Shark0s","playerId":"59dba5865d2de4db803703fc","roundScoreInPoints":4206,"distanceInMeters":262882.8886757751,"time":18,"lat":60.89872121861365,"lng":15.997049309828242},{"playerName":"Manumalada","playerId":"56a0744b93a14639dc49f6ec","roundScoreInPoints":4450,"distanceInMeters":177392.3286407527,"time":40,"lat":57.44804934082963,"lng":13.618105737923383},{"playerName":"Shark0s","playerId":"5be9cbd71f3cf81af810ab67","roundScoreInPoints":4545,"distanceInMeters":145040.5723038516,"time":17,"lat":59.9135689309466,"lng":14.997842655035072},{"playerName":"Vell","playerId":"5eea5f1162df1243a0cdd8e4","roundScoreInPoints":4108,"distanceInMeters":298761.8271116074,"time":14,"lat":56.35661065322525,"lng":13.75780766718799},{"playerName":"emi_1312","playerId":"5f931ed7c00e2400014430c9","roundScoreInPoints":4317,"distanceInMeters":223318.7940430812,"time":24,"lat":57.623953476902656,"lng":15.869980629757777},{"playerName":"\uD83D\uDC8B \uD83D\uDC8B \uD83D\uDC8B \uD83D\uDC8B","playerId":"5a4e3f8057f1750a400a8050","roundScoreInPoints":4314,"distanceInMeters":224313.828428062,"time":15,"lat":57.116411044023224,"lng":14.37568055986799},{"playerName":"Patagonia TV","playerId":"5f03b9a15b064d075036b8a4","roundScoreInPoints":3953,"distanceInMeters":357370.8732344868,"time":18,"lat":61.841523083019254,"lng":9.993895161865192},{"playerName":"Flop","playerId":"5f60e5f1f0ded50001af4007","roundScoreInPoints":4456,"distanceInMeters":175030.7191664108,"time":10,"lat":58.189187463201364,"lng":15.687976182632951},{"playerName":"Eldelsur","playerId":"60d6240f548abb000175df09","roundScoreInPoints":3888,"distanceInMeters":382590.2280274452,"time":21,"lat":58.14453546219756,"lng":6.737960108135206},{"playerName":"Marimil_","playerId":"6034d9d899166a0001e87efc","roundScoreInPoints":4405,"distanceInMeters":192788.4891941273,"time":16,"lat":57.972908304348834,"lng":15.765649502464054}],[{"playerName":"Dadge City","playerId":"5e81caa3d51dd62ccc447f85","roundScoreInPoints":4580,"distanceInMeters":133353.8661955171,"time":37,"lat":25.690927432727243,"lng":-103.01756102973667},{"playerName":"HugoCL","playerId":"5e8609cb3d4b6a3cf8dcfc9c","roundScoreInPoints":3043,"distanceInMeters":755306.7037423649,"time":12,"lat":28.49742141687532,"lng":-109.56897722447701},{"playerName":"Feliz cumplea\u00F1os Shark0s","playerId":"59dba5865d2de4db803703fc","roundScoreInPoints":4104,"distanceInMeters":300223.2165554348,"time":20,"lat":23.956421429889733,"lng":-102.54775498110595},{"playerName":"Manumalada","playerId":"56a0744b93a14639dc49f6ec","roundScoreInPoints":3381,"distanceInMeters":595201.7499316658,"time":32,"lat":29.955767770665393,"lng":-106.9694187145132},{"playerName":"Shark0s","playerId":"5be9cbd71f3cf81af810ab67","roundScoreInPoints":2430,"distanceInMeters":1097357.507701973,"time":40,"lat":31.131365187617742,"lng":-112.2401296030747},{"playerName":"Vell","playerId":"5eea5f1162df1243a0cdd8e4","roundScoreInPoints":4165,"distanceInMeters":277916.3417950014,"time":14,"lat":24.358720739259457,"lng":-103.33436236981402},{"playerName":"emi_1312","playerId":"5f931ed7c00e2400014430c9","roundScoreInPoints":4358,"distanceInMeters":209016.5841294865,"time":29,"lat":28.505108308054687,"lng":-101.95443098498484},{"playerName":"\uD83D\uDC8B \uD83D\uDC8B \uD83D\uDC8B \uD83D\uDC8B","playerId":"5a4e3f8057f1750a400a8050","roundScoreInPoints":3158,"distanceInMeters":698934.6165655969,"time":12,"lat":31.674111821079563,"lng":-106.50699981671448},{"playerName":"Patagonia TV","playerId":"5f03b9a15b064d075036b8a4","roundScoreInPoints":3681,"distanceInMeters":465756.9418474099,"time":26,"lat":22.451791610499274,"lng":-102.03256104326175},{"playerName":"Flop","playerId":"5f60e5f1f0ded50001af4007","roundScoreInPoints":242,"distanceInMeters":4604641.0285482025,"time":18,"lat":-7.614470295867716,"lng":-78.20037850653785},{"playerName":"Eldelsur","playerId":"60d6240f548abb000175df09","roundScoreInPoints":1370,"distanceInMeters":1969480.782483616,"time":21,"lat":37.594366110542865,"lng":-118.69961161248398},{"playerName":"Marimil_","playerId":"6034d9d899166a0001e87efc","roundScoreInPoints":59,"distanceInMeters":6745288.394218757,"time":16,"lat":-24.910181740483033,"lng":-69.05418722761209}]],"playerGames":[{"player":"Dadge City","playerId":"5e81caa3d51dd62ccc447f85","points":18071,"r1":{"points":3210,"time":34},"r2":{"points":3217,"time":40},"r3":{"points":2399,"time":35},"r4":{"points":4665,"time":40},"r5":{"points":4580,"time":37},"eliminatedInGame":null,"totalDistanceInMeters":2700294.5760928607,"totalTime":185,"pinUrl":"pin/436b2c79c893b097346d306d5da52da3.png"},{"player":"HugoCL","playerId":"5e8609cb3d4b6a3cf8dcfc9c","points":17520,"r1":{"points":4981,"time":40},"r2":{"points":1744,"time":20},"r3":{"points":3184,"time":11},"r4":{"points":4568,"time":17},"r5":{"points":3043,"time":12},"eliminatedInGame":null,"totalDistanceInMeters":3186787.8479469214,"totalTime":101,"pinUrl":"pin/e5f74cec7074031d7943fe18a1fcd4ee.png"},{"player":"Feliz cumplea\u00F1os Shark0s","playerId":"59dba5865d2de4db803703fc","points":16997,"r1":{"points":3486,"time":38},"r2":{"points":1895,"time":20},"r3":{"points":3306,"time":15},"r4":{"points":4206,"time":18},"r5":{"points":4104,"time":20},"eliminatedInGame":null,"totalDistanceInMeters":3216830.205707792,"totalTime":111,"pinUrl":"pin/47077cec4286dc7a5e9b45657bcb73c4.png"},{"player":"Manumalada","playerId":"56a0744b93a14639dc49f6ec","points":16324,"r1":{"points":2553,"time":40},"r2":{"points":1567,"time":40},"r3":{"points":4373,"time":29},"r4":{"points":4450,"time":40},"r5":{"points":3381,"time":32},"eliminatedInGame":null,"totalDistanceInMeters":3763486.287628405,"totalTime":181,"pinUrl":"pin/f4c77c636c7c3891a5380de6c8678546.png"},{"player":"Shark0s","playerId":"5be9cbd71f3cf81af810ab67","points":15981,"r1":{"points":3290,"time":32},"r2":{"points":1682,"time":26},"r3":{"points":4034,"time":35},"r4":{"points":4545,"time":17},"r5":{"points":2430,"time":40},"eliminatedInGame":null,"totalDistanceInMeters":3862047.459290299,"totalTime":151,"pinUrl":"pin/b713e0e3e92745f87336894f59565483.png"},{"player":"Vell","playerId":"5eea5f1162df1243a0cdd8e4","points":15689,"r1":{"points":0,"time":40},"r2":{"points":4212,"time":21},"r3":{"points":3204,"time":23},"r4":{"points":4108,"time":14},"r5":{"points":4165,"time":14},"eliminatedInGame":null,"totalDistanceInMeters":8469796.43612622,"totalTime":112,"pinUrl":"pin/8fc9180d0e9c6762387a828551e87899.png"},{"player":"emi_1312","playerId":"5f931ed7c00e2400014430c9","points":15578,"r1":{"points":2819,"time":37},"r2":{"points":479,"time":34},"r3":{"points":3605,"time":33},"r4":{"points":4317,"time":24},"r5":{"points":4358,"time":29},"eliminatedInGame":null,"totalDistanceInMeters":5369788.11595828,"totalTime":157,"pinUrl":"pin/7c973b63b16fc0e1e54da798df26d107.png"},{"player":"\uD83D\uDC8B \uD83D\uDC8B \uD83D\uDC8B \uD83D\uDC8B","playerId":"5a4e3f8057f1750a400a8050","points":14393,"r1":{"points":3286,"time":17},"r2":{"points":480,"time":20},"r3":{"points":3155,"time":10},"r4":{"points":4314,"time":15},"r5":{"points":3158,"time":12},"eliminatedInGame":null,"totalDistanceInMeters":5825402.74265501,"totalTime":75,"pinUrl":"pin/86f979e614ed4e7e515208a7507da65f.png"},{"player":"Patagonia TV","playerId":"5f03b9a15b064d075036b8a4","points":12967,"r1":{"points":4,"time":28},"r2":{"points":837,"time":33},"r3":{"points":4492,"time":18},"r4":{"points":3953,"time":18},"r5":{"points":3681,"time":26},"eliminatedInGame":null,"totalDistanceInMeters":14694521.45047454,"totalTime":123,"pinUrl":""},{"player":"Flop","playerId":"5f60e5f1f0ded50001af4007","points":10812,"r1":{"points":1,"time":20},"r2":{"points":2839,"time":17},"r3":{"points":3274,"time":11},"r4":{"points":4456,"time":10},"r5":{"points":242,"time":18},"eliminatedInGame":null,"totalDistanceInMeters":20230066.565225363,"totalTime":76,"pinUrl":"pin/050bba84581be36d79ab4a4d381c7b11.png"},{"player":"Eldelsur","playerId":"60d6240f548abb000175df09","points":8090,"r1":{"points":2831,"time":38},"r2":{"points":0,"time":40},"r3":{"points":1,"time":34},"r4":{"points":3888,"time":21},"r5":{"points":1370,"time":21},"eliminatedInGame":null,"totalDistanceInMeters":31602574.617789324,"totalTime":154,"pinUrl":"pin/c61de0306e98cff723346e205377c373.png"},{"player":"Marimil_","playerId":"6034d9d899166a0001e87efc","points":7646,"r1":{"points":2347,"time":26},"r2":{"points":834,"time":40},"r3":{"points":1,"time":29},"r4":{"points":4405,"time":16},"r5":{"points":59,"time":16},"eliminatedInGame":null,"totalDistanceInMeters":23428035.743824095,"totalTime":127,"pinUrl":""}],"answers":[{"lat":62.31896889443726,"lng":-7.1031326354868725,"countryCode":"FO","countryName":"Faroe Islands"},{"lat":-25.18033758904836,"lng":152.2215642878042,"countryCode":"AU","countryName":"Australia"},{"lat":-37.25852834321574,"lng":-61.258759668605364,"countryCode":"AR","countryName":"Argentina"},{"lat":59.02199349924096,"lng":13.12346066419002,"countryCode":"SE","countryName":"Sweden"},{"lat":26.63775994708748,"lng":-102.19745362678509,"countryCode":"MX","countryName":"Mexico"}],"mapName":"AI Made World Map [10000\u002B]","gameNumber":1,"gameUrl":"https://www.geoguessr.com/results/m1wkBa4wGgj9L4Hq","gameId":"m1wkBa4wGgj9L4Hq","gameDescription":"40 sec. No move","playedWithEliminations":false,"forbidMoving":true,"forbidRotating":false,"forbidZooming":false,"timeLimit":40}]}